etask/__init__.py
etask/emacs.py
etask/main.py
etask/path.py
etask/pinfo.py
etask/pprint.py
etask/task_generators.py
etask/tasks.py
etask-1.2.1.dist-info/METADATA
etask-1.2.1.dist-info/WHEEL
etask-1.2.1.dist-info/entry_points.txt
etask-1.2.1.dist-info/top_level.txt
etask-1.2.1.dist-info/RECORD
