Metadata-Version: 2.1
Name: etask
Version: 1.2.1
Summary: CLI interface to GNU Emacs
Home-page: https://gitlab.com/xgqt/python-etask
Author: Maciej Barć
Author-email: xgqt@riseup.net
License: GPL-2-or-later
Keywords: emacs
Requires-Python: >=3.6.*
Requires-Dist: colorama
